odoo/addons/l10n_es_genci_account/README.rst
odoo/addons/l10n_es_genci_account/__init__.py
odoo/addons/l10n_es_genci_account/__manifest__.py
odoo/addons/l10n_es_genci_account/data/data.xml
odoo/addons/l10n_es_genci_account/i18n/ca.po
odoo/addons/l10n_es_genci_account/i18n/es.po
odoo/addons/l10n_es_genci_account/models/__init__.py
odoo/addons/l10n_es_genci_account/models/account_fiscal_position.py
odoo/addons/l10n_es_genci_account/models/account_move.py
odoo/addons/l10n_es_genci_account/models/account_move_line.py
odoo/addons/l10n_es_genci_account/models/genci_capacity.py
odoo/addons/l10n_es_genci_account/models/genci_material.py
odoo/addons/l10n_es_genci_account/models/genci_rule.py
odoo/addons/l10n_es_genci_account/models/product_product.py
odoo/addons/l10n_es_genci_account/models/product_template.py
odoo/addons/l10n_es_genci_account/models/res_company.py
odoo/addons/l10n_es_genci_account/models/res_partner.py
odoo/addons/l10n_es_genci_account/readme/CONFIGURE.md
odoo/addons/l10n_es_genci_account/readme/CONTRIBUTORS.md
odoo/addons/l10n_es_genci_account/readme/DESCRIPTION.md
odoo/addons/l10n_es_genci_account/readme/INSTALL.md
odoo/addons/l10n_es_genci_account/readme/ROADMAP.md
odoo/addons/l10n_es_genci_account/readme/USAGE.md
odoo/addons/l10n_es_genci_account/report/report_invoice.xml
odoo/addons/l10n_es_genci_account/security/genci_groups.xml
odoo/addons/l10n_es_genci_account/security/ir.model.access.csv
odoo/addons/l10n_es_genci_account/static/description/icon.png
odoo/addons/l10n_es_genci_account/static/description/index.html
odoo/addons/l10n_es_genci_account/tests/__init__.py
odoo/addons/l10n_es_genci_account/tests/test_l10n_es_genci_account.py
odoo/addons/l10n_es_genci_account/views/account_fiscal_position_views.xml
odoo/addons/l10n_es_genci_account/views/account_move_views.xml
odoo/addons/l10n_es_genci_account/views/l10n_es_genci_views.xml
odoo/addons/l10n_es_genci_account/views/product_views.xml
odoo/addons/l10n_es_genci_account/views/res_company_views.xml
odoo_addon_l10n_es_genci_account-16.0.1.0.0.1.dist-info/METADATA
odoo_addon_l10n_es_genci_account-16.0.1.0.0.1.dist-info/WHEEL
odoo_addon_l10n_es_genci_account-16.0.1.0.0.1.dist-info/top_level.txt
odoo_addon_l10n_es_genci_account-16.0.1.0.0.1.dist-info/RECORD
